s3like/__init__.py
s3like/tests/__init__.py
s3like/tests/test_s3like.py
s3like-1.5.0.dist-info/METADATA
s3like-1.5.0.dist-info/WHEEL
s3like-1.5.0.dist-info/top_level.txt
s3like-1.5.0.dist-info/RECORD
