Metadata-Version: 2.1
Name: s3like
Version: 1.5.0
Summary: A small package that is used by COMP to read and write model results to S3 like object storage systems.
Home-page: https://github.com/comp-org/s3like
Author: Hank Doupe
Author-email: henrymdoupe@gmail.com
License: UNKNOWN
Platform: UNKNOWN
Classifier: Programming Language :: Python :: 3
Classifier: License :: OSI Approved :: GNU Affero General Public License v3
Classifier: Operating System :: OS Independent
Requires-Dist: marshmallow (>=3.*)
Requires-Dist: requests
Requires-Dist: boto3
